ducky_L/__init__.py
ducky_L/modulo.py
ducky_l-0.2.2.dist-info/METADATA
ducky_l-0.2.2.dist-info/WHEEL
ducky_l-0.2.2.dist-info/top_level.txt
ducky_l-0.2.2.dist-info/RECORD
