Metadata-Version: 2.4
Name: ducky_L
Version: 0.2.2
Summary: Lenguaje/libreria en español para programar divertido y fácil
Author: José Pato
Author-email: José Pato <patodequeso222@gmail.com>
Keywords: español,educativo,patos,lenguaje
Requires-Python: >=3.7
Dynamic: author
Dynamic: requires-python
